sqlmako/__init__.py
sqlmako/fields.py
sqlmako/model.py
sqlmako/queryset.py
sqlmako-0.0.1.dist-info/LICENSE
sqlmako-0.0.1.dist-info/METADATA
sqlmako-0.0.1.dist-info/WHEEL
sqlmako-0.0.1.dist-info/RECORD
