Metadata-Version: 2.1
Name: sqlmako
Version: 0.0.1
Summary: 
Author: rfzee
Author-email: rfzee@proton.me
Requires-Python: >=3.12,<4.0
Classifier: Programming Language :: Python :: 3
Classifier: Programming Language :: Python :: 3.12
Requires-Dist: loguru (>=0.7.2,<0.8.0)
Requires-Dist: pydantic (>=2.7.4,<3.0.0)
Requires-Dist: sqlmodel (>=0.0.18,<0.0.19)
